pygrille.py
text.py
pygrille-0.3.3.dist-info/LICENSE.txt
pygrille-0.3.3.dist-info/METADATA
pygrille-0.3.3.dist-info/WHEEL
pygrille-0.3.3.dist-info/top_level.txt
pygrille-0.3.3.dist-info/RECORD
