Metadata-Version: 2.1
Name: pygrille
Version: 0.3.3
Summary: A quick way to write and visualise any code involving grids of squares in python.
License-File: LICENSE.txt
Requires-Dist: pygame
